alignme/__init__.py
alignme/__main__.py
alignme/py.typed
alignme-0.1.0.dist-info/entry_points.txt
alignme-0.1.0.dist-info/LICENSE
alignme-0.1.0.dist-info/WHEEL
alignme-0.1.0.dist-info/METADATA
alignme-0.1.0.dist-info/RECORD
