Metadata-Version: 2.1
Name: alignme
Version: 0.1.0
Summary: Alignment Tool based on Biopython
Home-page: https://github.com/wxicu/alignme
License: MIT
Author: xichenwu
Author-email: xichenwu@outlook.com
Requires-Python: >=3.8.0,<4.0.0
Classifier: License :: OSI Approved :: MIT License
Classifier: Programming Language :: Python :: 3
Classifier: Programming Language :: Python :: 3.8
Classifier: Programming Language :: Python :: 3.9
Classifier: Programming Language :: Python :: 3.10
Classifier: Programming Language :: Python :: 3.10
Classifier: Programming Language :: Python :: 3.8
Classifier: Programming Language :: Python :: 3.9
Requires-Dist: PyYAML (>=5.4.1)
Requires-Dist: biopython (>=1.79,<2.0)
Requires-Dist: click (>=8.0.0)
Requires-Dist: rich (>=10.3.0)
Project-URL: Documentation, https://alignme.readthedocs.io
Project-URL: Repository, https://github.com/wxicu/alignme
